dtfilterthumbor/__init__.py
dtfilterthumbor/dtwatermark.py
dtfilterthumbor-1.1.1.dist-info/METADATA
dtfilterthumbor-1.1.1.dist-info/WHEEL
dtfilterthumbor-1.1.1.dist-info/top_level.txt
dtfilterthumbor-1.1.1.dist-info/RECORD
