Metadata-Version: 2.1
Name: dtfilterthumbor
Version: 1.1.1
Summary: dan tri filter
Home-page: https://medium-multiply.readthedocs.io/
Author: xuantrangk54
Author-email: xuantrangk54@gmail.com
License: MIT
Platform: UNKNOWN
Classifier: Intended Audience :: Developers
Classifier: License :: OSI Approved :: MIT License
Classifier: Programming Language :: Python
Classifier: Programming Language :: Python :: 3
Classifier: Programming Language :: Python :: 3.6
Classifier: Programming Language :: Python :: 3.7
Classifier: Programming Language :: Python :: 3.8
Classifier: Programming Language :: Python :: 3.9
Classifier: Operating System :: OS Independent
